stdlib_list-stubs/METADATA.toml
stdlib_list-stubs/__init__.pyi
stdlib_list-stubs/_version.pyi
stdlib_list-stubs/base.pyi
types_stdlib_list-0.8.3.3.dist-info/METADATA
types_stdlib_list-0.8.3.3.dist-info/WHEEL
types_stdlib_list-0.8.3.3.dist-info/top_level.txt
types_stdlib_list-0.8.3.3.dist-info/RECORD
